pydantic_loader/__init__.py
pydantic_loader/config.py
pydantic_loader/encode.py
pydantic_loader/toml_config.py
pydantic_loader/yaml_config.py
pydantic_loader-0.9.1.dist-info/LICENSE
pydantic_loader-0.9.1.dist-info/WHEEL
pydantic_loader-0.9.1.dist-info/METADATA
pydantic_loader-0.9.1.dist-info/RECORD
