Metadata-Version: 1.1
Name: pydantic_loader
Version: 0.9.1
Summary: pydantic loader module.
Home-page: https://github.com/sander76/pyconfig
Author: Sander Teunissen
Author-email: no_mail@nomail.com
